odoo/addons/l10n_it_fatturapa/README.rst
odoo/addons/l10n_it_fatturapa/__init__.py
odoo/addons/l10n_it_fatturapa/__manifest__.py
odoo/addons/l10n_it_fatturapa/controllers/__init__.py
odoo/addons/l10n_it_fatturapa/controllers/main.py
odoo/addons/l10n_it_fatturapa/data/FoglioStileAssoSoftware.xsl
odoo/addons/l10n_it_fatturapa/data/FoglioStileSouthTyrol-bilingue.xsl
odoo/addons/l10n_it_fatturapa/data/Foglio_di_stile_fatturaordinaria_v1.2.2.xsl
odoo/addons/l10n_it_fatturapa/data/fatturapa_data.xml
odoo/addons/l10n_it_fatturapa/data/fatturasemplificata_v1.0.xsl
odoo/addons/l10n_it_fatturapa/data/welfare.fund.type.csv
odoo/addons/l10n_it_fatturapa/demo/account_invoice_fatturapa.xml
odoo/addons/l10n_it_fatturapa/i18n/am.po
odoo/addons/l10n_it_fatturapa/i18n/ar.po
odoo/addons/l10n_it_fatturapa/i18n/bg.po
odoo/addons/l10n_it_fatturapa/i18n/bs.po
odoo/addons/l10n_it_fatturapa/i18n/ca.po
odoo/addons/l10n_it_fatturapa/i18n/cs.po
odoo/addons/l10n_it_fatturapa/i18n/da.po
odoo/addons/l10n_it_fatturapa/i18n/de.po
odoo/addons/l10n_it_fatturapa/i18n/el_GR.po
odoo/addons/l10n_it_fatturapa/i18n/en_GB.po
odoo/addons/l10n_it_fatturapa/i18n/es.po
odoo/addons/l10n_it_fatturapa/i18n/es_AR.po
odoo/addons/l10n_it_fatturapa/i18n/es_CL.po
odoo/addons/l10n_it_fatturapa/i18n/es_CO.po
odoo/addons/l10n_it_fatturapa/i18n/es_CR.po
odoo/addons/l10n_it_fatturapa/i18n/es_DO.po
odoo/addons/l10n_it_fatturapa/i18n/es_EC.po
odoo/addons/l10n_it_fatturapa/i18n/es_ES.po
odoo/addons/l10n_it_fatturapa/i18n/es_MX.po
odoo/addons/l10n_it_fatturapa/i18n/es_PE.po
odoo/addons/l10n_it_fatturapa/i18n/es_PY.po
odoo/addons/l10n_it_fatturapa/i18n/es_VE.po
odoo/addons/l10n_it_fatturapa/i18n/et.po
odoo/addons/l10n_it_fatturapa/i18n/eu.po
odoo/addons/l10n_it_fatturapa/i18n/fa.po
odoo/addons/l10n_it_fatturapa/i18n/fi.po
odoo/addons/l10n_it_fatturapa/i18n/fr.po
odoo/addons/l10n_it_fatturapa/i18n/fr_CA.po
odoo/addons/l10n_it_fatturapa/i18n/fr_CH.po
odoo/addons/l10n_it_fatturapa/i18n/fr_FR.po
odoo14_addon_l10n_it_fatturapa-14.0.2.4.0.dist-info/METADATA
odoo14_addon_l10n_it_fatturapa-14.0.2.4.0.dist-info/WHEEL
odoo14_addon_l10n_it_fatturapa-14.0.2.4.0.dist-info/top_level.txt
odoo14_addon_l10n_it_fatturapa-14.0.2.4.0.dist-info/RECORD
