Metadata-Version: 2.1
Name: odoo14-addon-l10n_it_fatturapa
Version: 14.0.2.4.0
Summary: Fatture elettroniche
Home-page: https://github.com/OCA/l10n-italy
Author: Davide Corio, Agile Business Group, Innoviu, Odoo Italia Network, Odoo Community Association (OCA)
Author-email: support@odoo-community.org
License: AGPL-3
Classifier: Programming Language :: Python
Classifier: Framework :: Odoo
Classifier: Framework :: Odoo :: 14.0
Classifier: License :: OSI Approved :: GNU Affero General Public License v3
Classifier: Development Status :: 4 - Beta
Requires-Python: >=3.6
Requires-Dist: asn1crypto
Requires-Dist: odoo14-addon-l10n-it-account
Requires-Dist: odoo14-addon-l10n-it-account-tax-kind
Requires-Dist: odoo14-addon-l10n-it-fiscal-payment-term
Requires-Dist: odoo14-addon-l10n-it-fiscalcode
Requires-Dist: odoo14-addon-l10n-it-ipa
Requires-Dist: odoo14-addon-l10n-it-rea
Requires-Dist: odoo14-addon-l10n-it-vat-payability
Requires-Dist: odoo14-addon-partner-firstname
Requires-Dist: odoo<14.1dev,>=14.0a
